{"ch2":{"GAME_VERSION":"0.052 beta"},"helpfulAdventurer":{"flavorClass":"The Helpful Adventurer","name":"Helpful Adventurer","flavor":"A character who uses her energy to empower rapid click attacks.","levelGraphObject":{"nodes":[{"1":{"x":-54,"val":"T1","y":-23}},{"2":{"x":1,"val":"T2","y":-97}},{"3":{"x":56,"val":"T3","y":-24}},{"4":{"x":1,"val":"T4","y":42}},{"5":{"x":1,"val":"T5","y":139}},{"6":{"x":1,"val":"A0","y":250}},{"7":{"x":-76,"val":"A5","y":150}},{"8":{"x":-147,"val":"T8","y":56}},{"9":{"x":-147,"val":"Au","y":-43}},{"10":{"x":-75,"val":"S3","y":-138}},{"11":{"x":2,"val":"T7","y":-237}},{"12":{"x":79,"val":"S2","y":-138}},{"13":{"x":149,"val":"Av","y":-44}},{"14":{"x":149,"val":"T6","y":53}},{"15":{"x":79,"val":"Se","y":150}},{"16":{"x":-174,"val":"Az","y":-188}},{"17":{"x":-358,"val":"Se","y":2}},{"18":{"x":-358,"val":"S8","y":-119}},{"19":{"x":-358,"val":"Sg","y":118}},{"20":{"x":174,"val":"Az","y":-187}},{"21":{"x":361,"val":"Sd","y":2}},{"22":{"x":361,"val":"S9","y":-118}},{"23":{"x":361,"val":"Sf","y":120}},{"24":{"x":-1278,"val":"Gp","y":46}},{"25":{"x":-265,"val":"A2","y":-231}},{"26":{"x":-178,"val":"Mt","y":-335}},{"27":{"x":-86,"val":"S4","y":-448}},{"28":{"x":-271,"val":"A8","y":237}},{"29":{"x":89,"val":"S6","y":-448}},{"30":{"x":184,"val":"Cd","y":-334}},{"31":{"x":266,"val":"A7","y":-234}},{"32":{"x":2,"val":"A6","y":-555}},{"33":{"x":-189,"val":"G","y":337}},{"34":{"x":-95,"val":"S5","y":444}},{"35":{"x":6,"val":"S1","y":551}},{"36":{"x":97,"val":"S7","y":440}},{"37":{"x":185,"val":"H","y":337}},{"38":{"x":262,"val":"A4","y":238}},{"39":{"x":-168,"val":"Az","y":193}},{"40":{"x":171,"val":"Az","y":192}},{"41":{"x":-582,"val":"Ir","y":-41}},{"42":{"x":321,"val":"I2","y":-1780}},{"43":{"x":172,"val":"Gc","y":-1144}},{"44":{"x":-23,"val":"Cc","y":-1119}},{"45":{"x":-216,"val":"Gp","y":-1099}},{"46":{"x":-292,"val":"Bd","y":-444}},{"47":{"x":-403,"val":"qMr","y":-549}},{"48":{"x":299,"val":"Cc","y":-444}},{"49":{"x":417,"val":"qCd","y":-550}},{"50":{"x":-292,"val":"Hd","y":422}},{"51":{"x":-403,"val":"qG","y":515}},{"52":{"x":298,"val":"Mu","y":424}},{"53":{"x":418,"val":"qH","y":515}},{"54":{"x":18,"val":"Gc","y":-2110}},{"55":{"x":172,"val":"Gp","y":-2085}},{"56":{"x":37,"val":"Mr","y":-1637}},{"57":{"x":358,"val":"Bd","y":-1474}},{"58":{"x":2095,"val":"Rh","y":-869}},{"59":{"x":319,"val":"Bc","y":-1620}},{"60":{"x":1318,"val":"I7","y":-125}},{"61":{"x":466,"val":"Cc","y":-2033}},{"62":{"x":594,"val":"I3","y":-2133}},{"63":{"x":-1294,"val":"Gc","y":219}},{"64":{"x":1286,"val":"Bg","y":-1857}},{"65":{"x":1440,"val":"Cl","y":-1874}},{"66":{"x":2008,"val":"Tg","y":-1567}},{"67":{"x":1597,"val":"Gc","y":-1881}},{"68":{"x":1448,"val":"H","y":-71}},{"69":{"x":1817,"val":"Gb","y":-1797}},{"70":{"x":1910,"val":"G","y":-1667}},{"71":{"x":1834,"val":"Bc","y":-1029}},{"72":{"x":2102,"val":"Mu","y":-589}},{"73":{"x":1425,"val":"Mu","y":-239}},{"74":{"x":661,"val":"Mu","y":-581}},{"75":{"x":764,"val":"H","y":-472}},{"76":{"x":1028,"val":"I8","y":-450}},{"77":{"x":-574,"val":"Gp","y":-178}},{"78":{"x":1756,"val":"I4","y":-463}},{"79":{"x":678,"val":"Pa","y":-784}},{"80":{"x":817,"val":"Cc","y":-893}},{"81":{"x":872,"val":"Pt","y":-1075}},{"82":{"x":2126,"val":"Hd","y":-730}},{"83":{"x":2132,"val":"H","y":-221}},{"84":{"x":2000,"val":"Bd","y":-271}},{"85":{"x":-51,"val":"Hd","y":1147}},{"86":{"x":-8,"val":"G","y":1011}},{"87":{"x":1886,"val":"Cd","y":-513}},{"88":{"x":1964,"val":"Md","y":-621}},{"89":{"x":322,"val":"Mt","y":-2051}},{"90":{"x":705,"val":"G","y":-2233}},{"91":{"x":1023,"val":"I4","y":-2038}},{"92":{"x":829,"val":"Cl","y":-2150}},{"93":{"x":976,"val":"Gp","y":-2161}},{"94":{"x":2091,"val":"Md","y":-1310}},{"95":{"x":2017,"val":"I8","y":-1189}},{"96":{"x":1956,"val":"Cd","y":-948}},{"97":{"x":1880,"val":"Kh","y":-1247}},{"98":{"x":2049,"val":"Md","y":-1052}},{"99":{"x":905,"val":"Md","y":-773}},{"100":{"x":1520,"val":"Pa","y":-449}},{"101":{"x":929,"val":"Cc","y":-585}},{"102":{"x":1041,"val":"Hd","y":-769}},{"103":{"x":1200,"val":"Kh","y":-202}},{"104":{"x":2173,"val":"Bc","y":-348}},{"105":{"x":815,"val":"I3","y":-1221}},{"106":{"x":1158,"val":"G","y":-701}},{"107":{"x":1159,"val":"Ra","y":-847}},{"108":{"x":988,"val":"Cd","y":-1176}},{"109":{"x":1560,"val":"Ir","y":-316}},{"110":{"x":641,"val":"Md","y":-2008}},{"111":{"x":1272,"val":"Ph","y":-923}},{"112":{"x":588,"val":"Cd","y":-1876}},{"113":{"x":1278,"val":"Tc","y":-1993}},{"114":{"x":879,"val":"Bc","y":-370}},{"115":{"x":482,"val":"Mr","y":-825}},{"116":{"x":334,"val":"Eh","y":-1318}},{"117":{"x":419,"val":"Ea","y":-993}},{"118":{"x":355,"val":"I1","y":-1153}},{"119":{"x":767,"val":"G","y":-1419}},{"120":{"x":903,"val":"Cc","y":-1335}},{"121":{"x":1163,"val":"Ir","y":-2087}},{"122":{"x":638,"val":"Cd","y":-1350}},{"123":{"x":513,"val":"Ph","y":-1247}},{"124":{"x":537,"val":"Md","y":-669}},{"125":{"x":1390,"val":"Md","y":-370}},{"126":{"x":1775,"val":"Mu","y":-118}},{"127":{"x":604,"val":"Hd","y":2161}},{"128":{"x":1911,"val":"I5","y":-169}},{"129":{"x":-686,"val":"Gc","y":55}},{"130":{"x":235,"val":"En","y":-1915}},{"131":{"x":-2134,"val":"qMt","y":613}},{"132":{"x":-1669,"val":"qEn","y":151}},{"133":{"x":-2133,"val":"qGp","y":971}},{"134":{"x":-2035,"val":"qIr","y":1045}},{"135":{"x":-2047,"val":"qGc","y":954}},{"136":{"x":-1933,"val":"Q43","y":782}},{"137":{"x":-1468,"val":"qHd","y":1153}},{"138":{"x":-1315,"val":"qIr","y":1274}},{"139":{"x":-13,"val":"qBd","y":2339}},{"140":{"x":-1535,"val":"qG","y":1405}},{"141":{"x":-1387,"val":"qG","y":966}},{"142":{"x":-1284,"val":"Q44","y":461}},{"143":{"x":-496,"val":"qGp","y":134}},{"144":{"x":-9,"val":"qH","y":2049}},{"145":{"x":-142,"val":"qMu","y":1549}},{"146":{"x":-816,"val":"qBg","y":832}},{"147":{"x":-465,"val":"qGb","y":1499}},{"148":{"x":-517,"val":"qHd","y":1208}},{"149":{"x":-618,"val":"Q42","y":1162}},{"150":{"x":-599,"val":"qTc","y":1267}},{"151":{"x":-1967,"val":"Q41","y":1664}},{"152":{"x":-1967,"val":"qHd","y":1955}},{"153":{"x":-283,"val":"qBd","y":2011}},{"154":{"x":-721,"val":"Q45","y":1921}},{"155":{"x":-512,"val":"qTg","y":1822}},{"156":{"x":-1256,"val":"qG","y":2103}},{"157":{"x":-534,"val":"qHd","y":2251}},{"158":{"x":-1365,"val":"qGb","y":1788}},{"159":{"x":-326,"val":"qH","y":818}},{"160":{"x":-1893,"val":"qMr","y":377}},{"161":{"x":-2028,"val":"I6","y":314}},{"162":{"x":-2162,"val":"Gc","y":359}},{"163":{"x":-2177,"val":"Gp","y":489}},{"164":{"x":-1851,"val":"G","y":572}},{"165":{"x":-1588,"val":"Mt","y":406}},{"166":{"x":-1694,"val":"Mr","y":281}},{"167":{"x":-1523,"val":"Ea","y":219}},{"168":{"x":-1141,"val":"Kh","y":399}},{"169":{"x":-1743,"val":"En","y":462}},{"170":{"x":-1395,"val":"Eh","y":335}},{"171":{"x":-1377,"val":"Gp","y":587}},{"172":{"x":-1498,"val":"Gc","y":694}},{"173":{"x":-1634,"val":"G","y":777}},{"174":{"x":-1424,"val":"Cd","y":828}},{"175":{"x":-1075,"val":"Cl","y":910}},{"176":{"x":-1701,"val":"Rh","y":1220}},{"177":{"x":-1626,"val":"I3","y":1080}},{"178":{"x":-1597,"val":"Ra","y":920}},{"179":{"x":-1523,"val":"G","y":1816}},{"180":{"x":-1576,"val":"Mr","y":1670}},{"181":{"x":-1228,"val":"I5","y":936}},{"182":{"x":-1785,"val":"Ph","y":1951}},{"183":{"x":-455,"val":"Hd","y":879}},{"184":{"x":-1172,"val":"Cd","y":560}},{"185":{"x":122,"val":"Hd","y":2068}},{"186":{"x":-2008,"val":"G","y":675}},{"187":{"x":-984,"val":"Bd","y":363}},{"188":{"x":-818,"val":"Bc","y":339}},{"189":{"x":-1031,"val":"Cc","y":616}},{"190":{"x":-526,"val":"Gp","y":409}},{"191":{"x":-660,"val":"Gc","y":329}},{"192":{"x":-635,"val":"I8","y":193}},{"193":{"x":-963,"val":"Gb","y":743}},{"194":{"x":-516,"val":"Ir","y":619}},{"195":{"x":-2187,"val":"I2","y":721}},{"196":{"x":-2180,"val":"Hd","y":849}},{"197":{"x":-1822,"val":"Hd","y":142}},{"198":{"x":-1968,"val":"Ra","y":162}},{"199":{"x":-757,"val":"Tg","y":699}},{"200":{"x":-236,"val":"Ir","y":1157}},{"201":{"x":-663,"val":"Tc","y":590}},{"202":{"x":-930,"val":"G","y":930}},{"203":{"x":-2147,"val":"Md","y":1755}},{"204":{"x":-200,"val":"Ea","y":892}},{"205":{"x":-179,"val":"Eh","y":1028}},{"206":{"x":-2088,"val":"Pa","y":1879}},{"207":{"x":-377,"val":"I1","y":1165}},{"208":{"x":-456,"val":"Bg","y":1059}},{"209":{"x":-566,"val":"G","y":971}},{"210":{"x":-669,"val":"Gb","y":870}},{"211":{"x":-1176,"val":"Hd","y":1069}},{"212":{"x":-1185,"val":"G","y":1209}},{"213":{"x":-1606,"val":"I7","y":1963}},{"214":{"x":-1248,"val":"Ea","y":1400}},{"215":{"x":-863,"val":"G","y":1901}},{"216":{"x":-395,"val":"Pa","y":2305}},{"217":{"x":-1426,"val":"Pt","y":2021}},{"218":{"x":-1077,"val":"Cc","y":2109}},{"219":{"x":-894,"val":"Cd","y":2165}},{"220":{"x":-712,"val":"Md","y":2207}},{"221":{"x":-897,"val":"Bd","y":2034}},{"222":{"x":-759,"val":"I2","y":1137}},{"223":{"x":-776,"val":"Tg","y":1264}},{"224":{"x":-794,"val":"Ir","y":1393}},{"225":{"x":-639,"val":"Gb","y":1392}},{"226":{"x":-353,"val":"Gp","y":1422}},{"227":{"x":-136,"val":"Mu","y":1269}},{"228":{"x":-321,"val":"G","y":1287}},{"229":{"x":-2097,"val":"Rh","y":204}},{"230":{"x":-109,"val":"H","y":1410}},{"231":{"x":-67,"val":"I3","y":1678}},{"232":{"x":-5,"val":"Bd","y":1797}},{"233":{"x":-194,"val":"Ea","y":1709}},{"234":{"x":-348,"val":"Gb","y":1743}},{"235":{"x":-358,"val":"Bg","y":1873}},{"236":{"x":-762,"val":"Bg","y":1530}},{"237":{"x":-290,"val":"Gc","y":1539}},{"238":{"x":45,"val":"Bc","y":1928}},{"239":{"x":-747,"val":"Ra","y":1672}},{"240":{"x":-427,"val":"Ph","y":2033}},{"241":{"x":180,"val":"Mu","y":2183}},{"242":{"x":117,"val":"H","y":2296}},{"243":{"x":-364,"val":"Pt","y":2161}},{"244":{"x":-124,"val":"Cl","y":2263}},{"245":{"x":-261,"val":"I5","y":2255}},{"246":{"x":-1750,"val":"Tg","y":925}},{"247":{"x":-1905,"val":"Tc","y":938}},{"248":{"x":-2157,"val":"Gc","y":1366}},{"249":{"x":-1636,"val":"En","y":1531}},{"250":{"x":-2151,"val":"Gp","y":1506}},{"251":{"x":-1046,"val":"Ra","y":1166}},{"252":{"x":-1748,"val":"Mt","y":1417}},{"253":{"x":-1942,"val":"G","y":1178}},{"254":{"x":-2102,"val":"I1","y":1248}},{"255":{"x":-2150,"val":"Cd","y":1110}},{"256":{"x":-899,"val":"Rh","y":1147}},{"257":{"x":-1848,"val":"Hd","y":1302}},{"258":{"x":-1962,"val":"Cd","y":1385}},{"259":{"x":-2116,"val":"I8","y":1634}},{"260":{"x":-299,"val":"H","y":632}},{"261":{"x":-197,"val":"Kh","y":744}},{"262":{"x":-534,"val":"Ir","y":1680}},{"263":{"x":-659,"val":"Rh","y":1778}},{"264":{"x":-1725,"val":"Cl","y":639}},{"265":{"x":-1944,"val":"Cc","y":1528}},{"266":{"x":-1785,"val":"I4","y":767}},{"267":{"x":-133,"val":"Eh","y":1824}},{"268":{"x":-1825,"val":"Hd","y":1714}},{"269":{"x":-1679,"val":"Cl","y":1771}},{"270":{"x":-404,"val":"I4","y":1626}},{"271":{"x":-1216,"val":"Gp","y":1838}},{"272":{"x":-1121,"val":"Gc","y":1965}},{"273":{"x":-866,"val":"Cd","y":1761}},{"274":{"x":-227,"val":"H","y":1905}},{"275":{"x":-1417,"val":"Eh","y":1492}},{"276":{"x":-1263,"val":"Kh","y":1547}},{"277":{"x":-1199,"val":"I6","y":1692}},{"278":{"x":-1034,"val":"Hd","y":1731}},{"279":{"x":-2065,"val":"Gb","y":809}},{"280":{"x":-817,"val":"Tc","y":1015}},{"281":{"x":963,"val":"Md","y":-1909}},{"282":{"x":582,"val":"Cl","y":-1575}},{"283":{"x":449,"val":"Cc","y":-1665}},{"284":{"x":1209,"val":"Cl","y":-1652}},{"285":{"x":1094,"val":"Cd","y":-1748}},{"286":{"x":1028,"val":"Md","y":-1427}},{"287":{"x":1057,"val":"I5","y":-1619}},{"288":{"x":1287,"val":"Pt","y":-1540}},{"289":{"x":1336,"val":"Cc","y":-1415}},{"290":{"x":1440,"val":"I2","y":-1086}},{"291":{"x":199,"val":"qG","y":1362}},{"292":{"x":478,"val":"qHd","y":1499}},{"293":{"x":475,"val":"Q81","y":798}},{"294":{"x":755,"val":"qH","y":927}},{"295":{"x":60,"val":"qBg","y":761}},{"296":{"x":1014,"val":"Q84","y":1248}},{"297":{"x":964,"val":"qCd","y":149}},{"298":{"x":666,"val":"qBd","y":1135}},{"299":{"x":870,"val":"qH","y":1369}},{"300":{"x":1142,"val":"qMu","y":721}},{"301":{"x":1344,"val":"qBc","y":956}},{"302":{"x":1676,"val":"Q86","y":1921}},{"303":{"x":1470,"val":"Q85","y":1299}},{"304":{"x":1834,"val":"Q83","y":309}},{"305":{"x":738,"val":"qTg","y":1780}},{"306":{"x":863,"val":"qIr","y":2063}},{"307":{"x":1300,"val":"qH","y":1529}},{"308":{"x":1439,"val":"qMu","y":1805}},{"309":{"x":819,"val":"qMu","y":991}},{"310":{"x":1452,"val":"qBd","y":2230}},{"311":{"x":2094,"val":"qHd","y":1346}},{"312":{"x":994,"val":"qH","y":846}},{"313":{"x":984,"val":"Q82","y":639}},{"314":{"x":980,"val":"qH","y":505}},{"315":{"x":1613,"val":"qH","y":903}},{"316":{"x":1844,"val":"Kh","y":173}},{"317":{"x":1714,"val":"Hd","y":1015}},{"318":{"x":1115,"val":"Cd","y":1429}},{"319":{"x":1585,"val":"H","y":1797}},{"320":{"x":1782,"val":"Bc","y":1641}},{"321":{"x":1415,"val":"Cl","y":2001}},{"322":{"x":989,"val":"Rh","y":2110}},{"323":{"x":1220,"val":"I6","y":1341}},{"324":{"x":836,"val":"Ph","y":67}},{"325":{"x":1983,"val":"Mu","y":1828}},{"326":{"x":1730,"val":"qCl","y":602}},{"327":{"x":1962,"val":"H","y":447}},{"328":{"x":1986,"val":"Cd","y":306}},{"329":{"x":1921,"val":"Kh","y":673}},{"330":{"x":1879,"val":"Cd","y":802}},{"331":{"x":1767,"val":"Mu","y":888}},{"332":{"x":1262,"val":"Pa","y":231}},{"333":{"x":1767,"val":"Bd","y":440}},{"334":{"x":807,"val":"Md","y":276}},{"335":{"x":1537,"val":"Cd","y":231}},{"336":{"x":1395,"val":"I7","y":274}},{"337":{"x":235,"val":"Ra","y":1181}},{"338":{"x":1155,"val":"Q88","y":1932}},{"339":{"x":865,"val":"I8","y":411}},{"340":{"x":543,"val":"Cd","y":421}},{"341":{"x":454,"val":"Cl","y":1189}},{"342":{"x":644,"val":"I5","y":667}},{"343":{"x":1139,"val":"Mu","y":428}},{"344":{"x":1686,"val":"En","y":756}},{"345":{"x":187,"val":"I2","y":1500}},{"346":{"x":302,"val":"Gp","y":1578}},{"347":{"x":441,"val":"Bc","y":1629}},{"348":{"x":885,"val":"H","y":1712}},{"349":{"x":990,"val":"Bd","y":1601}},{"350":{"x":1201,"val":"Mu","y":2228}},{"351":{"x":1684,"val":"Pt","y":179}},{"352":{"x":1290,"val":"Cl","y":687}},{"353":{"x":1114,"val":"G","y":2143}},{"354":{"x":1704,"val":"I1","y":1536}},{"355":{"x":1064,"val":"H","y":1834}},{"356":{"x":1644,"val":"Eh","y":1169}},{"357":{"x":1593,"val":"Ea","y":2186}},{"358":{"x":1153,"val":"Mu","y":1091}},{"359":{"x":2125,"val":"G","y":1474}},{"360":{"x":1505,"val":"Bd","y":1162}},{"361":{"x":1289,"val":"H","y":1118}},{"362":{"x":2103,"val":"Cl","y":1607}},{"363":{"x":2003,"val":"Kh","y":1697}},{"364":{"x":1434,"val":"Kh","y":1576}},{"365":{"x":2040,"val":"I5","y":1211}},{"366":{"x":82,"val":"Gb","y":1264}},{"367":{"x":708,"val":"Hd","y":404}},{"368":{"x":1030,"val":"Cl","y":343}},{"369":{"x":1574,"val":"Mu","y":1591}},{"370":{"x":1354,"val":"H","y":1390}},{"371":{"x":1335,"val":"I8","y":1892}},{"372":{"x":327,"val":"G","y":619}},{"373":{"x":1907,"val":"Mu","y":1256}},{"374":{"x":846,"val":"Cl","y":810}},{"375":{"x":827,"val":"Mu","y":671}},{"376":{"x":741,"val":"H","y":545}},{"377":{"x":471,"val":"Tc","y":1942}},{"378":{"x":428,"val":"Rh","y":1800}},{"379":{"x":723,"val":"Tg","y":2074}},{"380":{"x":1277,"val":"H","y":550}},{"381":{"x":302,"val":"Bg","y":1721}},{"382":{"x":2019,"val":"H","y":1057}},{"383":{"x":1966,"val":"Bd","y":915}},{"384":{"x":1627,"val":"H","y":426}},{"385":{"x":1524,"val":"Mu","y":497}},{"386":{"x":1426,"val":"Bc","y":591}},{"387":{"x":1133,"val":"Kh","y":908}},{"388":{"x":1053,"val":"Cl","y":1007}},{"389":{"x":1419,"val":"H","y":786}},{"390":{"x":1125,"val":"Bd","y":570}},{"391":{"x":1541,"val":"I4","y":694}},{"392":{"x":1168,"val":"Hd","y":1589}},{"393":{"x":135,"val":"Tc","y":989}},{"394":{"x":600,"val":"Hd","y":942}},{"395":{"x":445,"val":"Kh","y":927}},{"396":{"x":838,"val":"H","y":1168}},{"397":{"x":1197,"val":"Bg","y":2053}},{"398":{"x":1151,"val":"Mr","y":1223}},{"399":{"x":1712,"val":"H","y":2104}},{"400":{"x":592,"val":"I4","y":1414}},{"401":{"x":704,"val":"G","y":1495}},{"402":{"x":845,"val":"Cl","y":1527}},{"403":{"x":166,"val":"I1","y":860}},{"404":{"x":1756,"val":"Cl","y":1285}},{"405":{"x":485,"val":"Mu","y":1061}},{"406":{"x":578,"val":"Mt","y":1239}},{"407":{"x":935,"val":"I3","y":1067}},{"408":{"x":1907,"val":"qH","y":1604}},{"409":{"x":247,"val":"Tg","y":739}},{"410":{"x":1115,"val":"Cc","y":168}},{"411":{"x":70,"val":"Gc","y":1404}},{"412":{"x":730,"val":"Bc","y":1261}},{"413":{"x":1567,"val":"Cl","y":1028}},{"414":{"x":1349,"val":"Hd","y":1685}},{"415":{"x":1480,"val":"Bd","y":1449}},{"416":{"x":606,"val":"I3","y":1980}},{"417":{"x":297,"val":"H","y":901}},{"418":{"x":616,"val":"H","y":795}},{"419":{"x":107,"val":"Ir","y":1123}},{"420":{"x":1267,"val":"G","y":841}},{"421":{"x":1319,"val":"Hd","y":1243}},{"422":{"x":341,"val":"Mu","y":1270}},{"423":{"x":1719,"val":"Hd","y":1749}},{"424":{"x":466,"val":"H","y":1338}},{"425":{"x":1419,"val":"I2","y":1063}},{"426":{"x":1247,"val":"H","y":1790}},{"427":{"x":1648,"val":"Cd","y":1418}},{"428":{"x":329,"val":"Q87","y":1080}},{"429":{"x":978,"val":"Mu","y":1464}},{"430":{"x":530,"val":"Bd","y":592}},{"431":{"x":588,"val":"G","y":1817}},{"432":{"x":1091,"val":"Mu","y":1698}},{"433":{"x":1789,"val":"I7","y":1998}},{"434":{"x":731,"val":"H","y":164}},{"435":{"x":1323,"val":"Kh","y":2257}},{"436":{"x":1532,"val":"G","y":2075}},{"437":{"x":1863,"val":"I6","y":543}},{"438":{"x":1897,"val":"Bd","y":1925}},{"439":{"x":1609,"val":"H","y":1296}},{"440":{"x":1411,"val":"qHd","y":407}},{"441":{"x":814,"val":"qH","y":-672}},{"442":{"x":808,"val":"qBd","y":-2013}},{"443":{"x":471,"val":"Q63","y":-1807}},{"444":{"x":940,"val":"Q64","y":-1553}},{"445":{"x":714,"val":"qBd","y":-1780}},{"446":{"x":719,"val":"qMd","y":-1552}},{"447":{"x":1057,"val":"qCd","y":-1280}},{"448":{"x":1437,"val":"qCd","y":-557}},{"449":{"x":1789,"val":"qCd","y":-1365}},{"450":{"x":1060,"val":"qCl","y":-1050}},{"451":{"x":1292,"val":"qCd","y":-1050}},{"452":{"x":1666,"val":"Q61","y":-558}},{"453":{"x":941,"val":"qCd","y":-1775}},{"454":{"x":1290,"val":"qMd","y":-1277}},{"455":{"x":1436,"val":"Q66","y":-780}},{"456":{"x":1665,"val":"qMd","y":-781}},{"457":{"x":428,"val":"qEn","y":-2174}},{"458":{"x":511,"val":"qMr","y":-1457}},{"459":{"x":632,"val":"qHd","y":-412}},{"460":{"x":1132,"val":"qGb","y":-1868}},{"461":{"x":2107,"val":"qIr","y":-1452}},{"462":{"x":990,"val":"Q62","y":-920}},{"463":{"x":1474,"val":"Q65","y":-1278}},{"464":{"x":1590,"val":"qMu","y":-100}},{"465":{"x":2073,"val":"qH","y":-450}},{"466":{"x":559,"val":"qMt","y":-1068}},{"467":{"x":1551,"val":"qG","y":-1689}},{"468":{"x":1230,"val":"qBd","y":-593}},{"469":{"x":1699,"val":"qCl","y":-973}},{"470":{"x":1836,"val":"qBd","y":-277}},{"471":{"x":-2042,"val":"Q27","y":-914}},{"472":{"x":-1699,"val":"Q26","y":-571}},{"473":{"x":-1439,"val":"Q30","y":-1476}},{"474":{"x":-1120,"val":"qMt","y":-1148}},{"475":{"x":-857,"val":"Q24","y":-698}},{"476":{"x":-1932,"val":"qBd","y":-1750}},{"477":{"x":-342,"val":"qCd","y":-2262}},{"478":{"x":-2033,"val":"qGc","y":-592}},{"479":{"x":-1685,"val":"qIr","y":-250}},{"480":{"x":-1874,"val":"qMt","y":-747}},{"481":{"x":-1111,"val":"qMr","y":-826}},{"482":{"x":-848,"val":"qTg","y":-376}},{"483":{"x":-1922,"val":"Q25","y":-1428}},{"484":{"x":-333,"val":"Q28","y":-1940}},{"485":{"x":-2022,"val":"Q23","y":-365}},{"486":{"x":-1679,"val":"qBg","y":-23}},{"487":{"x":-1910,"val":"qGp","y":-473}},{"488":{"x":-1100,"val":"Q21","y":-599}},{"489":{"x":-837,"val":"qG","y":-149}},{"490":{"x":-1912,"val":"qGp","y":-1201}},{"491":{"x":-322,"val":"qMd","y":-1713}},{"492":{"x":-1565,"val":"qGc","y":-1545}},{"493":{"x":-1637,"val":"qEn","y":-1291}},{"494":{"x":-1801,"val":"Q29","y":-1138}},{"495":{"x":-462,"val":"qBd","y":-1896}},{"496":{"x":-419,"val":"qCl","y":-1683}},{"497":{"x":-582,"val":"qBd","y":-930}},{"498":{"x":-1054,"val":"qEn","y":-2030}},{"499":{"x":-602,"val":"Q22","y":-1479}},{"500":{"x":-592,"val":"qCd","y":-1157}},{"501":{"x":-2115,"val":"Cd","y":-501}},{"502":{"x":-2154,"val":"I6","y":-620}},{"503":{"x":-2174,"val":"Mu","y":-748}},{"504":{"x":-2169,"val":"Kh","y":-882}},{"505":{"x":-1518,"val":"I3","y":-60}},{"506":{"x":-1532,"val":"Mr","y":-187}},{"507":{"x":-1412,"val":"Rh","y":-327}},{"508":{"x":-1303,"val":"Ra","y":-429}},{"509":{"x":-1819,"val":"Hd","y":-1311}},{"510":{"x":-1566,"val":"Md","y":-315}},{"511":{"x":-1174,"val":"Bg","y":-117}},{"512":{"x":-1546,"val":"En","y":-437}},{"513":{"x":-1528,"val":"Mt","y":-567}},{"514":{"x":-1593,"val":"I5","y":-676}},{"515":{"x":-1814,"val":"Gp","y":-216}},{"516":{"x":-1824,"val":"Eh","y":-332}},{"517":{"x":-1740,"val":"G","y":-786}},{"518":{"x":-1616,"val":"Gc","y":-846}},{"519":{"x":-1904,"val":"Pt","y":-911}},{"520":{"x":-2122,"val":"I8","y":-1012}},{"521":{"x":-2142,"val":"Cc","y":-378}},{"522":{"x":-2101,"val":"I4","y":-257}},{"523":{"x":-2125,"val":"Pt","y":-1132}},{"524":{"x":-2103,"val":"Ph","y":-1254}},{"525":{"x":-2051,"val":"Pa","y":-1378}},{"526":{"x":-2042,"val":"G","y":-1511}},{"527":{"x":-1780,"val":"Cd","y":-1787}},{"528":{"x":-1773,"val":"Cd","y":-657}},{"529":{"x":-1889,"val":"Cc","y":-599}},{"530":{"x":-1528,"val":"H","y":-1680}},{"531":{"x":-1819,"val":"Mu","y":-1526}},{"532":{"x":-1588,"val":"Md","y":-1415}},{"533":{"x":-1733,"val":"I1","y":-1416}},{"534":{"x":-445,"val":"Mr","y":-1523}},{"535":{"x":-1626,"val":"Ir","y":-1799}},{"536":{"x":-1153,"val":"I2","y":-453}},{"537":{"x":-1374,"val":"Gc","y":-575}},{"538":{"x":-1068,"val":"G","y":-323}},{"539":{"x":-1002,"val":"Gb","y":-180}},{"540":{"x":-969,"val":"Gp","y":-471}},{"541":{"x":-715,"val":"Tc","y":-222}},{"542":{"x":-643,"val":"Tg","y":-347}},{"543":{"x":-1243,"val":"Gp","y":-644}},{"544":{"x":-1324,"val":"Cc","y":-765}},{"545":{"x":-1945,"val":"Gc","y":-245}},{"546":{"x":-774,"val":"I8","y":-820}},{"547":{"x":-1984,"val":"Bd","y":-810}},{"548":{"x":-1386,"val":"Eh","y":-1055}},{"549":{"x":-827,"val":"Cl","y":-952}},{"550":{"x":-975,"val":"Ea","y":-889}},{"551":{"x":-1226,"val":"Kh","y":-1255}},{"552":{"x":-1492,"val":"Mu","y":-782}},{"553":{"x":-1904,"val":"Rh","y":-1026}},{"554":{"x":-2005,"val":"Ra","y":-1104}},{"555":{"x":-1525,"val":"Ea","y":-1092}},{"556":{"x":-1509,"val":"Mr","y":-1226}},{"557":{"x":-1416,"val":"En","y":-909}},{"558":{"x":-1257,"val":"Cd","y":-880}},{"559":{"x":-1316,"val":"Gc","y":-1350}},{"560":{"x":-1364,"val":"I2","y":-1190}},{"561":{"x":-1164,"val":"Bd","y":-1521}},{"562":{"x":-1298,"val":"I3","y":-1486}},{"563":{"x":-1769,"val":"I7","y":-916}},{"564":{"x":-1636,"val":"Gp","y":-976}},{"565":{"x":-1665,"val":"Md","y":-1114}},{"566":{"x":-1144,"val":"Rh","y":-1376}},{"567":{"x":-992,"val":"Ra","y":-1419}},{"568":{"x":-1463,"val":"Gp","y":-1351}},{"569":{"x":-1349,"val":"Ir","y":-76}},{"570":{"x":-690,"val":"Mt","y":-1869}},{"571":{"x":-738,"val":"Pa","y":-2067}},{"572":{"x":-685,"val":"En","y":-1726}},{"573":{"x":-443,"val":"I7","y":-1202}},{"574":{"x":-593,"val":"I5","y":-1985}},{"575":{"x":-503,"val":"Gp","y":-2093}},{"576":{"x":-306,"val":"Pa","y":-1450}},{"577":{"x":-217,"val":"Pt","y":-1570}},{"578":{"x":-166,"val":"I6","y":-1714}},{"579":{"x":-343,"val":"Gc","y":-2116}},{"580":{"x":-197,"val":"Cd","y":-2018}},{"581":{"x":-145,"val":"Kh","y":-1863}},{"582":{"x":-122,"val":"Cc","y":-2134}},{"583":{"x":-197,"val":"Md","y":-2233}},{"584":{"x":-501,"val":"Ph","y":-2231}},{"585":{"x":-639,"val":"Pt","y":-2174}},{"586":{"x":-571,"val":"Md","y":-1627}},{"587":{"x":-1822,"val":"Tc","y":-7}},{"588":{"x":-811,"val":"G","y":-1653}},{"589":{"x":-2036,"val":"G","y":-147}},{"590":{"x":-909,"val":"Cl","y":-1147}},{"591":{"x":-1007,"val":"Mu","y":-1631}},{"592":{"x":-475,"val":"Cc","y":-795}},{"593":{"x":-1193,"val":"H","y":-1957}},{"594":{"x":-1008,"val":"En","y":-1243}},{"595":{"x":-980,"val":"Mt","y":-1029}},{"596":{"x":-1394,"val":"Eh","y":-1733}},{"597":{"x":-1995,"val":"Cl","y":-1638}},{"598":{"x":-1915,"val":"Tg","y":-107}},{"599":{"x":-2055,"val":"Bc","y":-716}},{"600":{"x":-895,"val":"Kh","y":-2073}},{"601":{"x":-635,"val":"Mu","y":-762}},{"602":{"x":-1192,"val":"Bc","y":-1669}},{"603":{"x":-499,"val":"H","y":-1378}},{"604":{"x":-690,"val":"Eh","y":-1018}},{"605":{"x":-432,"val":"Cd","y":-941}},{"606":{"x":-383,"val":"Kh","y":-1074}},{"607":{"x":-751,"val":"Mr","y":-1168}},{"608":{"x":-365,"val":"Ph","y":-1310}},{"609":{"x":-1020,"val":"Kh","y":-716}},{"610":{"x":-951,"val":"Gc","y":-601}},{"611":{"x":-1084,"val":"Gp","y":-1759}},{"612":{"x":-894,"val":"I4","y":-1528}},{"613":{"x":-744,"val":"Hd","y":-1519}},{"614":{"x":-1787,"val":"Ea","y":-448}},{"615":{"x":-1036,"val":"Gc","y":-1893}},{"616":{"x":-1344,"val":"Ea","y":-1615}},{"617":{"x":-1304,"val":"Bd","y":-1847}},{"618":{"x":-724,"val":"I1","y":-448}},{"619":{"x":-598,"val":"G","y":-541}},{"620":{"x":-514,"val":"En","y":-660}},{"621":{"x":1779,"val":"Ra","y":-1607}},{"622":{"x":1704,"val":"Pt","y":-1483}},{"623":{"x":1398,"val":"Md","y":-1687}},{"624":{"x":1448,"val":"Bd","y":-1546}},{"625":{"x":1514,"val":"I7","y":-1419}},{"626":{"x":1427,"val":"Md","y":-910}},{"627":{"x":1575,"val":"Pa","y":-1164}},{"628":{"x":1740,"val":"Hd","y":-1218}},{"629":{"x":1626,"val":"Cd","y":-1323}},{"630":{"x":1845,"val":"Cc","y":-705}},{"631":{"x":1795,"val":"I1","y":-844}},{"632":{"x":1665,"val":"Hd","y":-222}},{"633":{"x":1939,"val":"Kh","y":-390}},{"634":{"x":1024,"val":"Bd","y":-290}},{"635":{"x":601,"val":"Pt","y":-1703}},{"636":{"x":1169,"val":"H","y":-346}},{"637":{"x":1229,"val":"Cl","y":-462}},{"638":{"x":1548,"val":"Ir","y":-765}},{"639":{"x":1582,"val":"Cd","y":-893}},{"640":{"x":1550,"val":"I6","y":-634}},{"641":{"x":323,"val":"Kh","y":2218}},{"642":{"x":468,"val":"Bc","y":2206}},{"643":{"x":666,"val":"Md","y":-1159}},{"644":{"x":1168,"val":"G","y":-1144}},{"645":{"x":1316,"val":"Cl","y":-1171}},{"646":{"x":1536,"val":"Cc","y":-1001}},{"647":{"x":1145,"val":"G","y":-1513}},{"648":{"x":1701,"val":"Cl","y":-670}},{"649":{"x":817,"val":"Rh","y":-1657}},{"650":{"x":827,"val":"Pa","y":-1799}},{"651":{"x":1180,"val":"Cd","y":-1383}},{"652":{"x":1288,"val":"Cd","y":-755}},{"653":{"x":1401,"val":"Bd","y":-673}},{"654":{"x":1684,"val":"H","y":-359}},{"655":{"x":1942,"val":"Pt","y":-808}},{"656":{"x":1692,"val":"Md","y":-1093}},{"657":{"x":737,"val":"Kh","y":-1907}},{"658":{"x":1669,"val":"I6","y":-1766}},{"659":{"x":732,"val":"Cl","y":-1018}},{"660":{"x":680,"val":"Bd","y":-171}},{"661":{"x":736,"val":"H","y":-41}},{"662":{"x":1526,"val":"Cd","y":39}},{"663":{"x":1418,"val":"Mu","y":129}},{"664":{"x":2116,"val":"Cd","y":-84}},{"665":{"x":2124,"val":"Md","y":55}},{"666":{"x":2070,"val":"H","y":186}},{"667":{"x":-75,"val":"Cd","y":-1535}},{"668":{"x":177,"val":"Md","y":-1577}},{"669":{"x":-2151,"val":"Gc","y":-67}},{"670":{"x":-2024,"val":"Bd","y":23}},{"671":{"x":175,"val":"Ir","y":1699}},{"672":{"x":59,"val":"Hd","y":1616}},{"673":{"x":-2150,"val":"Gp","y":88}},{"674":{"x":771,"val":"Cd","y":-276}},{"776":{"x":-344,"val":"Ay","y":-681}},{"777":{"x":-236,"val":"Ax","y":-587}},{"778":{"x":362,"val":"Ay","y":-723}},{"779":{"x":250,"val":"Aw","y":-633}},{"780":{"x":219,"val":"Ay","y":526}},{"781":{"x":129,"val":"Ax","y":628}},{"782":{"x":-184,"val":"Ay","y":540}},{"783":{"x":-93,"val":"Aw","y":647}}],"edges":[{"1":[561,566]},{"2":[549,604]},{"3":[164,169]},{"4":[258,265]},{"5":[327,328]},{"6":[327,437]},{"7":[155,263]},{"8":[579,580]},{"9":[334,434]},{"10":[37,38]},{"11":[337,419]},{"12":[491,578]},{"13":[297,324]},{"14":[81,108]},{"15":[474,594]},{"16":[334,339]},{"17":[590,607]},{"18":[284,288]},{"19":[253,254]},{"20":[385,440]},{"21":[172,173]},{"22":[227,230]},{"23":[630,655]},{"24":[374,375]},{"25":[119,446]},{"26":[155,262]},{"27":[576,577]},{"28":[634,636]},{"29":[492,532]},{"30":[281,453]},{"31":[486,505]},{"32":[320,408]},{"33":[492,530]},{"34":[26,46]},{"35":[487,614]},{"36":[115,117]},{"37":[422,424]},{"38":[338,355]},{"39":[455,626]},{"40":[190,191]},{"41":[146,210]},{"42":[165,169]},{"43":[152,206]},{"44":[184,189]},{"45":[527,535]},{"46":[393,419]},{"47":[56,668]},{"48":[472,514]},{"49":[239,273]},{"50":[396,407]},{"51":[365,373]},{"52":[181,211]},{"53":[77,541]},{"54":[320,354]},{"55":[474,551]},{"56":[60,103]},{"57":[343,368]},{"58":[394,395]},{"59":[321,371]},{"60":[501,502]},{"61":[294,394]},{"62":[66,461]},{"63":[361,421]},{"64":[6,7]},{"65":[237,270]},{"66":[572,586]},{"67":[41,77]},{"68":[612,613]},{"69":[51,190]},{"70":[42,130]},{"71":[71,469]},{"72":[590,594]},{"73":[115,124]},{"74":[627,656]},{"75":[574,575]},{"76":[275,276]},{"77":[580,582]},{"78":[21,22]},{"79":[185,241]},{"80":[72,88]},{"81":[21,23]},{"82":[132,197]},{"83":[780,781]},{"84":[364,369]},{"85":[643,659]},{"86":[160,161]},{"87":[66,70]},{"88":[248,254]},{"89":[488,543]},{"90":[342,376]},{"91":[343,390]},{"92":[400,424]},{"93":[131,163]},{"94":[591,611]},{"95":[131,195]},{"96":[308,371]},{"97":[144,185]},{"98":[138,214]},{"99":[84,633]},{"100":[388,407]},{"101":[142,168]},{"102":[213,217]},{"103":[140,275]},{"104":[305,431]},{"105":[381,671]},{"106":[222,223]},{"107":[471,519]},{"108":[85,86]},{"109":[513,537]},{"110":[253,257]},{"111":[109,654]},{"112":[559,562]},{"113":[291,345]},{"114":[179,269]},{"115":[67,658]},{"116":[179,180]},{"117":[101,441]},{"118":[20,31]},{"119":[323,370]},{"120":[479,515]},{"121":[345,411]},{"122":[396,412]},{"123":[249,252]},{"124":[287,444]},{"125":[330,331]},{"126":[355,432]},{"127":[288,289]},{"128":[333,384]},{"129":[176,257]},{"130":[530,596]},{"131":[243,245]},{"132":[179,213]},{"133":[561,602]},{"134":[229,673]},{"135":[469,639]},{"136":[433,438]},{"137":[41,129]},{"138":[564,565]},{"139":[387,388]},{"140":[609,610]},{"141":[4,5]},{"142":[115,778]},{"143":[218,219]},{"144":[336,663]},{"145":[307,392]},{"146":[127,379]},{"147":[517,563]},{"148":[329,330]},{"149":[479,510]},{"150":[552,557]},{"151":[200,205]},{"152":[592,605]},{"153":[638,639]},{"154":[268,269]},{"155":[119,122]},{"156":[164,264]},{"157":[204,261]},{"158":[28,33]},{"159":[530,535]},{"160":[267,274]},{"161":[262,270]},{"162":[140,249]},{"163":[290,627]},{"164":[575,579]},{"165":[42,59]},{"166":[147,226]},{"167":[335,351]},{"168":[618,619]},{"169":[318,323]},{"170":[146,202]},{"171":[400,401]},{"172":[24,63]},{"173":[578,581]},{"174":[603,608]},{"175":[511,539]},{"176":[619,620]},{"177":[73,125]},{"178":[371,426]},{"179":[361,425]},{"180":[159,183]},{"181":[480,517]},{"182":[34,35]},{"183":[401,402]},{"184":[224,236]},{"185":[100,109]},{"186":[481,558]},{"187":[83,104]},{"188":[553,554]},{"189":[393,403]},{"190":[135,247]},{"191":[638,640]},{"192":[496,586]},{"193":[550,595]},{"194":[180,249]},{"195":[215,273]},{"196":[231,672]},{"197":[23,38]},{"198":[264,266]},{"199":[310,357]},{"200":[515,516]},{"201":[387,420]},{"202":[596,617]},{"203":[219,220]},{"204":[660,661]},{"205":[74,75]},{"206":[531,533]},{"207":[588,612]},{"208":[329,437]},{"209":[555,565]},{"210":[548,557]},{"211":[53,372]},{"212":[43,44]},{"213":[96,655]},{"214":[88,630]},{"215":[141,174]},{"216":[379,416]},{"217":[9,10]},{"218":[562,616]},{"219":[551,560]},{"220":[142,170]},{"221":[476,597]},{"222":[549,550]},{"223":[102,106]},{"224":[45,606]},{"225":[97,628]},{"226":[477,584]},{"227":[498,615]},{"228":[126,128]},{"229":[42,443]},{"230":[3,4]},{"231":[56,667]},{"232":[477,583]},{"233":[413,425]},{"234":[65,67]},{"235":[328,666]},{"236":[38,40]},{"237":[7,8]},{"238":[175,202]},{"239":[43,118]},{"240":[377,416]},{"241":[102,107]},{"242":[145,231]},{"243":[301,425]},{"244":[306,322]},{"245":[5,6]},{"246":[339,367]},{"247":[311,365]},{"248":[520,523]},{"249":[358,361]},{"250":[51,194]},{"251":[57,59]},{"252":[561,562]},{"253":[6,15]},{"254":[158,179]},{"255":[226,237]},{"256":[24,569]},{"257":[106,468]},{"258":[521,522]},{"259":[127,642]},{"260":[283,635]},{"261":[304,328]},{"262":[475,546]},{"263":[292,347]},{"264":[2,3]},{"265":[354,427]},{"266":[547,599]},{"267":[324,434]},{"268":[323,398]},{"269":[365,382]},{"270":[487,529]},{"271":[366,411]},{"272":[95,97]},{"273":[518,552]},{"274":[489,539]},{"275":[214,276]},{"276":[494,565]},{"277":[78,452]},{"278":[566,567]},{"279":[377,378]},{"280":[167,170]},{"281":[543,544]},{"282":[282,283]},{"283":[44,45]},{"284":[503,504]},{"285":[303,439]},{"286":[482,618]},{"287":[128,470]},{"288":[346,347]},{"289":[151,265]},{"290":[636,637]},{"291":[350,435]},{"292":[395,417]},{"293":[114,674]},{"294":[134,253]},{"295":[64,460]},{"296":[72,465]},{"297":[402,429]},{"298":[782,783]},{"299":[519,563]},{"300":[358,388]},{"301":[202,280]},{"302":[91,281]},{"303":[149,222]},{"304":[233,267]},{"305":[99,102]},{"306":[150,225]},{"307":[378,381]},{"308":[670,673]},{"309":[35,36]},{"310":[86,393]},{"311":[61,89]},{"312":[87,88]},{"313":[644,645]},{"314":[131,186]},{"315":[232,238]},{"316":[665,666]},{"317":[548,560]},{"318":[623,624]},{"319":[582,583]},{"320":[330,383]},{"321":[548,555]},{"322":[630,631]},{"323":[505,569]},{"324":[640,648]},{"325":[325,438]},{"326":[628,629]},{"327":[96,98]},{"328":[318,429]},{"329":[481,609]},{"330":[285,460]},{"331":[324,661]},{"332":[28,39]},{"333":[53,340]},{"334":[165,166]},{"335":[50,51]},{"336":[372,780]},{"337":[522,589]},{"338":[621,622]},{"339":[79,124]},{"340":[476,527]},{"341":[290,451]},{"342":[577,578]},{"343":[404,439]},{"344":[97,449]},{"345":[271,272]},{"346":[340,367]},{"347":[30,31]},{"348":[525,526]},{"349":[641,642]},{"350":[486,587]},{"351":[596,616]},{"352":[384,385]},{"353":[482,540]},{"354":[188,191]},{"355":[288,624]},{"356":[105,120]},{"357":[497,605]},{"358":[212,251]},{"359":[153,274]},{"360":[512,513]},{"361":[290,645]},{"362":[152,182]},{"363":[580,581]},{"364":[161,229]},{"365":[276,277]},{"366":[100,125]},{"367":[590,595]},{"368":[63,170]},{"369":[116,118]},{"370":[222,280]},{"371":[135,279]},{"372":[515,545]},{"373":[108,450]},{"374":[14,15]},{"375":[363,408]},{"376":[652,653]},{"377":[385,386]},{"378":[536,538]},{"379":[133,196]},{"380":[203,259]},{"381":[546,549]},{"382":[442,657]},{"383":[157,216]},{"384":[295,403]},{"385":[187,188]},{"386":[352,389]},{"387":[380,390]},{"388":[592,620]},{"389":[235,274]},{"390":[94,461]},{"391":[123,643]},{"392":[103,636]},{"393":[445,635]},{"394":[315,331]},{"395":[298,406]},{"396":[591,612]},{"397":[331,344]},{"398":[70,621]},{"399":[500,573]},{"400":[142,184]},{"401":[94,95]},{"402":[567,612]},{"403":[241,641]},{"404":[151,259]},{"405":[177,178]},{"406":[148,207]},{"407":[104,465]},{"408":[240,243]},{"409":[359,362]},{"410":[510,512]},{"411":[506,510]},{"412":[195,196]},{"413":[346,381]},{"414":[145,230]},{"415":[372,409]},{"416":[572,588]},{"417":[15,40]},{"418":[10,16]},{"419":[117,118]},{"420":[47,620]},{"421":[336,440]},{"422":[483,531]},{"423":[191,192]},{"424":[312,387]},{"425":[605,606]},{"426":[137,177]},{"427":[495,574]},{"428":[446,649]},{"429":[85,227]},{"430":[252,257]},{"431":[260,782]},{"432":[132,166]},{"433":[473,562]},{"434":[467,623]},{"435":[199,201]},{"436":[317,331]},{"437":[414,426]},{"438":[226,228]},{"439":[211,212]},{"440":[573,606]},{"441":[146,193]},{"442":[366,419]},{"443":[87,633]},{"444":[95,98]},{"445":[126,632]},{"446":[484,580]},{"447":[463,625]},{"448":[509,533]},{"449":[62,90]},{"450":[139,242]},{"451":[322,353]},{"452":[345,346]},{"453":[537,543]},{"454":[364,414]},{"455":[406,412]},{"456":[282,458]},{"457":[186,279]},{"458":[10,11]},{"459":[528,529]},{"460":[79,80]},{"461":[13,14]},{"462":[78,654]},{"463":[113,121]},{"464":[332,336]},{"465":[8,9]},{"466":[507,508]},{"467":[308,319]},{"468":[156,218]},{"469":[490,509]},{"470":[11,12]},{"471":[33,34]},{"472":[183,209]},{"473":[626,646]},{"474":[142,171]},{"475":[80,659]},{"476":[290,646]},{"477":[532,533]},{"478":[248,250]},{"479":[332,410]},{"480":[84,128]},{"481":[223,224]},{"482":[317,413]},{"483":[570,572]},{"484":[337,428]},{"485":[22,31]},{"486":[74,124]},{"487":[151,268]},{"488":[319,423]},{"489":[161,162]},{"490":[182,213]},{"491":[194,201]},{"492":[516,614]},{"493":[375,376]},{"494":[671,672]},{"495":[25,26]},{"496":[216,245]},{"497":[76,114]},{"498":[246,247]},{"499":[311,359]},{"500":[69,658]},{"501":[18,25]},{"502":[277,278]},{"503":[80,462]},{"504":[17,18]},{"505":[157,220]},{"506":[478,502]},{"507":[175,181]},{"508":[627,628]},{"509":[26,27]},{"510":[323,421]},{"511":[378,431]},{"512":[542,618]},{"513":[386,391]},{"514":[176,177]},{"515":[380,386]},{"516":[576,608]},{"517":[53,430]},{"518":[218,272]},{"519":[456,631]},{"520":[538,539]},{"521":[172,174]},{"522":[286,647]},{"523":[129,192]},{"524":[349,429]},{"525":[316,351]},{"526":[382,383]},{"527":[650,657]},{"528":[59,668]},{"529":[350,353]},{"530":[231,232]},{"531":[335,336]},{"532":[559,568]},{"533":[71,96]},{"534":[341,406]},{"535":[286,447]},{"536":[305,348]},{"537":[480,547]},{"538":[488,536]},{"539":[399,433]},{"540":[354,369]},{"541":[662,663]},{"542":[310,435]},{"543":[117,466]},{"544":[625,629]},{"545":[171,172]},{"546":[46,47]},{"547":[284,287]},{"548":[485,522]},{"549":[669,670]},{"550":[55,89]},{"551":[450,644]},{"552":[312,374]},{"553":[545,589]},{"554":[62,110]},{"555":[69,70]},{"556":[584,585]},{"557":[776,777]},{"558":[481,550]},{"559":[497,604]},{"560":[100,448]},{"561":[493,556]},{"562":[204,205]},{"563":[519,553]},{"564":[273,278]},{"565":[501,521]},{"566":[76,634]},{"567":[403,417]},{"568":[502,503]},{"569":[254,255]},{"570":[514,552]},{"571":[302,433]},{"572":[112,445]},{"573":[293,418]},{"574":[133,255]},{"575":[342,418]},{"576":[118,123]},{"577":[503,599]},{"578":[357,399]},{"579":[91,121]},{"580":[339,368]},{"581":[138,212]},{"582":[344,391]},{"583":[389,391]},{"584":[260,261]},{"585":[534,586]},{"586":[19,28]},{"587":[49,124]},{"588":[362,363]},{"589":[60,68]},{"590":[105,643]},{"591":[320,423]},{"592":[234,270]},{"593":[7,39]},{"594":[517,528]},{"595":[392,432]},{"596":[287,647]},{"597":[571,600]},{"598":[313,390]},{"599":[289,651]},{"600":[72,82]},{"601":[563,564]},{"602":[573,608]},{"603":[57,116]},{"604":[300,352]},{"605":[12,20]},{"606":[540,610]},{"607":[299,429]},{"608":[132,167]},{"609":[222,256]},{"610":[593,617]},{"611":[403,409]},{"612":[160,169]},{"613":[12,13]},{"614":[364,415]},{"615":[156,217]},{"616":[341,405]},{"617":[81,659]},{"618":[589,669]},{"619":[630,648]},{"620":[231,233]},{"621":[200,207]},{"622":[624,625]},{"623":[99,441]},{"624":[532,568]},{"625":[333,437]},{"626":[109,632]},{"627":[120,447]},{"628":[143,192]},{"629":[664,665]},{"630":[306,379]},{"631":[207,228]},{"632":[601,620]},{"633":[61,457]},{"634":[326,437]},{"635":[33,50]},{"636":[136,266]},{"637":[296,398]},{"638":[48,49]},{"639":[92,442]},{"640":[325,363]},{"641":[360,425]},{"642":[342,430]},{"643":[110,112]},{"644":[64,65]},{"645":[250,259]},{"646":[92,93]},{"647":[570,574]},{"648":[198,229]},{"649":[36,37]},{"650":[338,397]},{"651":[660,674]},{"652":[499,613]},{"653":[524,525]},{"654":[29,30]},{"655":[209,210]},{"656":[215,221]},{"657":[58,82]},{"658":[146,199]},{"659":[208,209]},{"660":[483,525]},{"661":[37,52]},{"662":[89,130]},{"663":[68,464]},{"664":[490,554]},{"665":[449,622]},{"666":[244,245]},{"667":[246,266]},{"668":[357,436]},{"669":[144,238]},{"670":[640,653]},{"671":[27,32]},{"672":[508,536]},{"673":[589,598]},{"674":[499,603]},{"675":[348,349]},{"676":[546,601]},{"677":[292,400]},{"678":[464,632]},{"679":[197,198]},{"680":[297,410]},{"681":[52,53]},{"682":[489,541]},{"683":[356,439]},{"684":[141,181]},{"685":[189,193]},{"686":[173,266]},{"687":[389,420]},{"688":[271,277]},{"689":[91,93]},{"690":[534,576]},{"691":[513,514]},{"692":[68,662]},{"693":[236,239]},{"694":[517,518]},{"695":[111,451]},{"696":[577,667]},{"697":[504,520]},{"698":[17,19]},{"699":[173,178]},{"700":[314,339]},{"701":[54,55]},{"702":[224,225]},{"703":[29,32]},{"704":[61,62]},{"705":[307,364]},{"706":[16,25]},{"707":[592,776]},{"708":[153,240]},{"709":[106,652]},{"710":[30,48]},{"711":[75,114]},{"712":[356,360]},{"713":[507,510]},{"714":[556,560]},{"715":[154,215]},{"716":[557,558]},{"717":[64,113]},{"718":[76,101]},{"719":[51,260]},{"720":[54,582]},{"721":[544,558]},{"722":[162,163]},{"723":[83,84]},{"724":[78,87]},{"725":[454,651]},{"726":[239,263]},{"727":[1,2]},{"728":[251,256]},{"729":[107,111]},{"730":[498,593]},{"731":[395,405]},{"732":[83,664]},{"733":[57,458]},{"734":[122,123]},{"735":[505,506]},{"736":[257,258]},{"737":[448,640]},{"738":[468,637]},{"739":[778,779]},{"740":[90,92]},{"741":[511,569]},{"742":[587,598]},{"743":[309,407]},{"744":[71,656]},{"745":[337,422]},{"746":[649,650]},{"747":[370,415]},{"748":[541,542]},{"749":[321,436]},{"750":[168,187]},{"751":[304,316]},{"752":[500,607]},{"753":[241,242]},{"754":[571,574]},{"755":[200,227]},{"756":[284,285]},{"757":[158,271]},{"758":[373,404]},{"759":[139,244]},{"760":[498,600]},{"761":[353,397]},{"762":[234,235]},{"763":[602,611]},{"764":[427,439]},{"765":[75,459]},{"766":[58,96]},{"767":[467,658]},{"768":[551,566]},{"769":[611,615]},{"770":[219,221]},{"771":[471,520]},{"772":[159,204]},{"773":[526,597]},{"774":[523,524]},{"775":[207,208]},{"776":[203,206]},{"777":[60,73]},{"778":[571,585]}]},"flavorName":"Cid","levelGraphNodeTypes":{"I7":{"tooltip":"Multiplies the damage you deal with boots by 150%","icon":"damageFeet","flavorText":null,"name":"Equipment: Boots"},"Q87":{"tooltip":"Huge Click, when activated, also triggers on every 20th click for the next 100 clicks.","icon":"damagex3","flavorText":null,"name":"Hecaton's Echo"},"T6":{"tooltip":"Causes your clicks within 60 seconds to deal 200% damage.","icon":"powersurgeDamage","flavorText":null,"name":"Skill: Powersurge"},"Cc":{"tooltip":"Increases your chance to score a critical hit by 2%.","icon":"critChance","flavorText":"Ever wonder what happens when you get over 100% Crit Chance? The Ancients once knew, but that is ancient history.","name":"Crit Chance"},"Gp":{"tooltip":"Multiplies the number of gold piles found by 110%.","icon":"goldPiles","flavorText":"This only affects piles of gold. Not other clickables.","name":"Gold Piles"},"Ax":{"tooltip":"Switch to the previous Automator Set.","icon":"gemSwitchPrev","flavorText":null,"name":"Automator Gem: Previous Set"},"qMu":{"tooltip":"Adds 9 clicks to your multiclick, at the cost of 3 additional energy.","icon":"nineClicks","flavorText":null,"name":"Mega Increased MultiClicks"},"Sd":{"tooltip":"A stone that can activate once every 8 seconds.","icon":"CD8S","flavorText":null,"name":"Automator Stone: 8s CD"},"Q43":{"tooltip":"Reload also returns your current gold to the amount you had at the beginning of the zone, then increases it by Reload's bonus.","icon":"damagex3","flavorText":null,"name":"Reload Rampage"},"Bd":{"tooltip":"Multiplies the damage done by Big Clicks by 125%","icon":"bigClicks","flavorText":"They might not look any bigger when you get this upgrade. They're bigger on the inside. In fact, they weigh a lot more.","name":"Bigger Big Clicks"},"Q88":{"tooltip":"Consumes 10 energy per second to click 30 times per second, until you run out of energy.","icon":"damagex3","flavorText":"Replaces Clickstorm.","name":"ClickTorrent"},"Q44":{"tooltip":"Reload reduces the cooldown of the next skill used by 50%.","icon":"damagex3","flavorText":null,"name":"Preload"},"T7":{"tooltip":"Clicks with a 100% chance to score a critical hit.","icon":"manaClick","flavorText":"It stacks. Everything stacks.","name":"Skill: Mana Crit"},"qBc":{"tooltip":"Increases the number of clicks empowered by Big Clicks by 3.","icon":"bigClicks","flavorText":null,"name":"Mega More Big Clicks"},"Ay":{"tooltip":"Unlocks an additional set for the Automator.","icon":"gemAddSet","flavorText":null,"name":"Automator Set"},"A0":{"tooltip":"Unlocks the Automator.","icon":"automator","flavorText":null,"name":"Automator"},"T8":{"tooltip":"Restores energy and mana and reduces the remaining cooldown of all skills by 10%.","icon":"reload","flavorText":null,"name":"Skill: Reload"},"En":{"tooltip":"Increases your maximum energy by 25.","icon":"totalEnergy","flavorText":"If a fixed amount is added to a number many times, that number is said to grow \"linearly\". This is because if you plot it out on an x/y graph, you'll see a line.","name":"Total Energy"},"Se":{"tooltip":"A stone that can activate once every 40 seconds.","icon":"CD40S","flavorText":null,"name":"Automator Stone: 40s CD"},"Kh":{"tooltip":"Multiplies the cooldown of Clickstorm by 0.8","icon":"clickstorm","flavorText":"If a fixed positive amount less than 1 is multiplied to a number many times, that number is said to \"approach zero\". Enough applications and your number will get very close to, but never actually reach, zero.","name":"Hastened Clickstorm"},"Mu":{"tooltip":"Adds 3 clicks to your multiclick, at the cost of 1 additional energy.","icon":"nineClicks","flavorText":"No matter how many of these upgrades you get, MultiClick will take the same amount of time to perform all of its clicks.","name":"Increased MultiClicks"},"Q45":{"tooltip":"Reload's effects and cooldown are reduced by 90%.","icon":"damagex3","flavorText":null,"name":"Quick Reload"},"A1":{"tooltip":"Automates MultiClick.","icon":"gemNineClicks","flavorText":null,"name":"Automator Gem: MultiClick"},"I3":{"tooltip":"Multiplies the damage you deal with chest pieces by 150%","icon":"damageTop","flavorText":null,"name":"Equipment: Chest"},"qBd":{"tooltip":"Increases the damage done by Big Clicks by 95%","icon":"bigClicks","flavorText":null,"name":"Mega Bigger Big Clicks"},"Eh":{"tooltip":"Multiplies the cooldown and mana cost of Energize by 0.8","icon":"energize","flavorText":"If a fixed positive amount less than 1 is multiplied to a number many times, that number is said to \"approach zero\". Enough applications and your number will get very close to, but never actually reach, zero.","name":"Hastened Energize"},"qG":{"tooltip":"Multiplies your gold received from all sources by 133%.","icon":"goldx3","flavorText":null,"name":"Mammon's Greed"},"Ea":{"tooltip":"Increases the duration of Energize by 20% of its original duration.","icon":"energize","flavorText":null,"name":"Improved Energize"},"Az":{"tooltip":"Speeds up the Automator by 25%.","icon":"automatorSpeed","flavorText":null,"name":"Automator Speed"},"qHd":{"tooltip":"Increases the damage of Huge Click by 95%","icon":"hugeClicks","flavorText":null,"name":"Mega Huger Huge Click"},"Cd":{"tooltip":"Multiplies the damage of your critical hits by 120%.","icon":"critDamage","flavorText":"When a number is multiplied by a fixed amount (greater than 1) many times, that number is said to grow \"exponentially\". This is because that process is usually represented by a formula that uses exponential notation.","name":"Crit Damage"},"Q61":{"tooltip":"Scoring a Critical Hit reduces the remaining cooldown of Mana Crit by 1 second.","icon":"damagex3","flavorText":"Casting a cooldown-improved Mana Crit will reset the cooldown of your *next* Mana Crit to its original duration.","name":"Bhaal's Rise"},"Sf":{"tooltip":"A stone that can activate once every 90 seconds.","icon":"CD90S","flavorText":null,"name":"Automator Stone: 90s CD"},"S1":{"tooltip":"A stone that can always activate.","icon":"always","flavorText":null,"name":"Automator Stone: Always"},"A3":{"tooltip":"Automates Big Clicks.","icon":"gemGameBigClicks","flavorText":null,"name":"Automator Gem: Big Clicks"},"qCd":{"tooltip":"Multiplies the damage of your critical hits by 172.8%.","icon":"critDamage","flavorText":null,"name":"Precision of Bhaal"},"I5":{"tooltip":"Multiplies the damage you deal with pants by 150%","icon":"damageLegs","flavorText":"Pants shouldn't do damage, that's ridiculous.","name":"Equipment: Pants"},"Mr":{"tooltip":"Multiplies your mana regeneration rate by 110%.","icon":"manaRegen","flavorText":"You will get 10% more mana per minute than before you had this upgrade.","name":"Mana Regeneration"},"qMd":{"tooltip":"Mana Crits do 95% more damage","icon":"manaClick","flavorText":null,"name":"Mega Mana Crit Damage"},"qH":{"tooltip":"Multiplies your Haste by 115.7%.","icon":"haste","flavorText":"Haste affects the rate that you auto-attack, and all cooldown speeds, including Automator cooldown speeds.","name":"Vaagur's Impatience"},"Ph":{"tooltip":"Multiplies the cooldown and mana cost of Powersurge by 0.8","icon":"powersurgeDuration","flavorText":"If a fixed positive amount less than 1 is multiplied to a number many times, that number is said to \"approach zero\". Enough applications and your number will get very close to, but never actually reach, zero.","name":"Hastened Powersurge"},"Gc":{"tooltip":"Multiplies your gold received from clickables by 150%.","icon":"clickableGold","flavorText":"If only someone could click on them before they go off the screen.","name":"Clickable Gold"},"Q62":{"tooltip":"Crit Chance increases the damage of Mana Crit and gives a chance to refund its mana cost.","icon":"damagex3","flavorText":null,"name":"Improved Mana Crit"},"Sg":{"tooltip":"A stone that can activate once every 10 minutes.","icon":"CD10M","flavorText":null,"name":"Automator Stone: 10m CD"},"S2":{"tooltip":"A stone that can activate when the next monster's health is greater than 50%.","icon":"mhGreater50","flavorText":null,"name":"Automator Stone: MH > 50%"},"A5":{"tooltip":"Automates Huge Click.","icon":"gemHugeClicks","flavorText":null,"name":"Automator Gem: Huge Click"},"qGc":{"tooltip":"Multiplies your gold received from clickables by 337.5%.","icon":"clickableGold","flavorText":null,"name":"Revolc's Blessing"},"Q21":{"tooltip":"Skills do not interrupt Auto Attacks.","icon":"damagex3","flavorText":null,"name":"Synchrony"},"Q63":{"tooltip":"Monsters killed with a Critical Hit reduces the cooldown of Powersurge by 5 seconds.","icon":"damagex3","flavorText":"Casting a cooldown-improved Powersurge will reset the cooldown of your *next* Powersurge to its original duration.","name":"Critical Killing Surge"},"Pt":{"tooltip":"Multiplies the duration of Powersurge by 120%.","icon":"powersurgeDuration","flavorText":null,"name":"Sustained Powersurge"},"Pc":{"tooltip":"Increases your chance to hit an additional monster by 1%.","icon":"pierceChance","flavorText":null,"name":"Pierce Chance (NOT IN GAME)"},"S3":{"tooltip":"A stone that can activate when the next monster's health is less than 50%.","icon":"mhLower50","flavorText":null,"name":"Automator Stone: MH < 50%"},"A4":{"tooltip":"Automates Clickstorm.","icon":"gemClickstorm","flavorText":null,"name":"Automator Gem: Clickstorm"},"Pa":{"tooltip":"Multiplies the damage bonus of Powersurge by 125%.","icon":"powersurgeDamage","flavorText":null,"name":"Improved Powersurge"},"qCl":{"tooltip":"Multiplies your click damage by 133%.","icon":"clickDamage","flavorText":null,"name":"The Wrath of Fragsworth"},"Q22":{"tooltip":"Damage is increased by 100% while you have less than 60% of your total energy.","icon":"damagex3","flavorText":null,"name":"Release"},"Q64":{"tooltip":"Overkill from Mana Crit damages the next monster.","icon":"damagex3","flavorText":"It will not spill damage over to more than one additional monster.","name":"Mana Crit Overflow"},"Test":{"tooltip":"Easy access test nodes that you can find scattered throughout the tree.","icon":"","flavorText":null,"name":"Test Cheats","alwaysAvailable":true},"qGb":{"tooltip":"Multiplies your gold received from bosses by 800%.","icon":"bossGold","flavorText":null,"name":"Mimzee's Kindness"},"Q23":{"tooltip":"Gold gained is increased by 100% while you have more than 40% of your total energy.","icon":"damagex3","flavorText":null,"name":"Restraint"},"I6":{"tooltip":"Multiplies the damage you deal with gloves by 150%","icon":"damageHands","flavorText":null,"name":"Equipment: Gloves"},"I2":{"tooltip":"Multiplies the damage you deal with helmets by 150%","icon":"damageHead","flavorText":null,"name":"Equipment: Helmet"},"S4":{"tooltip":"A stone that can activate when your energy is above 90%.","icon":"energyGreater90","flavorText":null,"name":"Automator Stone: Energy > 90%"},"Av":{"tooltip":"Automates Upgrading the Cheapest Item.","icon":"gemUpgradeCheapest","flavorText":null,"name":"Automator Gem: Upgrade Cheapest Item"},"q":{"tooltip":"Let Hotara know if you spot one","icon":"damagex3","flavorText":null,"name":"These should no longer exist"},"Tp":{"tooltip":"(GONE) Increases the number of talent points you start the world with by 1.","icon":"talentPoint","flavorText":null,"name":"Talent Point"},"Mt":{"tooltip":"Increases your maximum mana by 25.","icon":"totalMana","flavorText":"If a fixed amount is added to a number many times, that number is said to grow \"linearly\". This is because if you plot it out on an x/y graph, you'll see a line.","name":"Total Mana"},"Q65":{"tooltip":"Consumes 1.25 energy per second to click 2.5 times per second, until you run out of energy. Clicks from this skill have +100% chance of being critical strikes.","icon":"damagex3","flavorText":"Replaces Clickstorm.","name":"CritStorm"},"Q24":{"tooltip":"Spending energy deals damage equal to one click per energy.","icon":"damagex3","flavorText":null,"name":"Discharge"},"Ra":{"tooltip":"Increases the effect of Reload by 10%.","icon":"improvedReload","flavorText":null,"name":"Improved Reload"},"qIr":{"tooltip":"Reduces the cost of buying and leveling items by 22%.","icon":"itemCostReduction","flavorText":null,"name":"The Thrift of Dogcog"},"Mo":{"tooltip":"Collect Clickables by mousing over them instead of clicking them","icon":"clickableGold","flavorText":"The ancients left some of their greatest powers behind for you to discover.","name":"Mousing over Clickables"},"S5":{"tooltip":"A stone that can activate when your energy is below 10%.","icon":"energyLower10","flavorText":null,"name":"Automator Stone: Energy < 10%"},"Au":{"tooltip":"Automates Buying a Random Catalog Item.","icon":"gemBuyRandom","flavorText":"The Catalog is that area on the bottom left of the UI where you purchase new items.","name":"Automator Gem: Buy Random Catalog"},"I4":{"tooltip":"Multiplies the damage you deal with rings by 150%","icon":"damageAccesory","flavorText":null,"name":"Equipment: Ring"},"qMt":{"tooltip":"Increases your maximum Mana by 100.","icon":"totalMana","flavorText":null,"name":"Energon's Ions"},"Q25":{"tooltip":"Spending mana increases haste for 5 seconds.","icon":"damagex3","flavorText":null,"name":"Gift of Chronos"},"Ir":{"tooltip":"Multiplies the gold costs of buying and leveling equipment by 0.92.","icon":"itemCostReduction","flavorText":"Rufus sometimes wonders why he can't compete in the Gold market. He always felt like there was a mysterious seller undercutting him.","name":"Item Cost Reduction"},"Q66":{"tooltip":"PowerSurge, upon activating, decreases Crit Chance by 100%, and then increases Crit Chance by 5% every second until it ends.","icon":"damagex3","flavorText":null,"name":"Critical Powersurge"},"I8":{"tooltip":"Multiplies the damage you deal with capes by 150%","icon":"damageBack","flavorText":"If you wear these in real life, people will think something is wrong with you.","name":"Equipment: Capes"},"Rh":{"tooltip":"Multiplies the cooldown of Reload by 0.8","icon":"hastenReload","flavorText":null,"name":"Hastened Reload"},"Q81":{"tooltip":"Removes the 1-second minimum limit on Global Cooldown, allowing Haste to reduce it below 1 second.","icon":"damagex3","flavorText":null,"name":"Limitless Haste"},"qCc":{"tooltip":"This Node does not actually exist in the game.","icon":"critChance","flavorText":null,"name":"+20% Crit Chance"},"I1":{"tooltip":"Multiplies the damage you deal with weapons by 150%","icon":"damageWeapon","flavorText":null,"name":"Equipment: Weapon"},"S6":{"tooltip":"A stone that can activate when your mana is above 90%.","icon":"manaGreater90","flavorText":null,"name":"Automator Stone: Mana > 90%"},"Q26":{"tooltip":"While Big Clicks is active, all skills cost 1 additional energy per skill that has been activated since Big Clicks began.","icon":"damagex3","flavorText":null,"name":"Curse of the Juggernaut"},"Gb":{"tooltip":"Multiplies your gold received from bosses by 200%.","icon":"bossGold","flavorText":"If you're tired of farming bosses, this will roughly cut it in half. Can you prove this?","name":"Boss Gold"},"Tg":{"tooltip":"Multiplies the gold received from treasure chest monsters by 125%.","icon":"treasureGold","flavorText":null,"name":"Treasure Chest Gold"},"A2":{"tooltip":"Automates Energize.","icon":"gemEnergize","flavorText":null,"name":"Automator Gem: Energize."},"qMr":{"tooltip":"Multiplies your mana regeneration by 133%.","icon":"manaRegen","flavorText":null,"name":"Energon's Grace"},"Q82":{"tooltip":"Haste increases the number of clicks in a MultiClick by the percentage of haste you have.","icon":"damagex3","flavorText":"Rounded up or rounded down? Only the Ancients know.","name":"Flurry"},"G":{"tooltip":"Multiplies your gold received from all sources by 110%.","icon":"goldx3","flavorText":"We can also say that it is multiplied by 1.1, but that sounds so much weaker.","name":"Gold"},"T3":{"tooltip":"Clicks 5 times.","icon":"nineClicks","flavorText":null,"name":"Skill: MultiClick"},"qEn":{"tooltip":"Increases your maximum Energy by 100.","icon":"totalEnergy","flavorText":null,"name":"Juggernaut's Pittance"},"Q27":{"tooltip":"Big Clicks has no cooldown and can stack infinitely.","icon":"damagex3","flavorText":null,"name":"Limitless Big Clicks"},"S7":{"tooltip":"A stone that can activate when your mana is below 10%.","icon":"manaLower10","flavorText":null,"name":"Automator Stone: Mana < 10%"},"Nc":{"tooltip":"Multiplies your damage from MultiClicks by 2","icon":"nineClicks","flavorText":null,"name":"MultiClick"},"H":{"tooltip":"Multiplies your Haste by 105%.","icon":"haste","flavorText":"Haste affects the rate that you auto-attack, and all cooldown speeds, including Automator cooldown speeds.","name":"Haste"},"A6":{"tooltip":"Automates Powersurge.","icon":"gemPowersurge","flavorText":null,"name":"Automator Gem: Powersurge."},"Cl":{"tooltip":"Multiplies your click damage by 110%.","icon":"clickDamage","flavorText":"This affects damage from all skills that \"click\". But it does not affect auto-attacks, because those are not \"clicks\".","name":"Click Damage"},"T1":{"tooltip":"Causes your next 6 clicks to deal 300% damage.","icon":"bigClicks","flavorText":"When activated, press your mouse button harder for added effect.","name":"Skill: Big Clicks","alwaysAvailable":true},"Q83":{"tooltip":"Gain 100% haste upon killing a monster. Lasts 5 seconds, quickly decreasing over time.","icon":"damagex3","flavorText":null,"name":"Killing Frenzy"},"Q28":{"tooltip":"Critical Hits from Auto Attacks restore 1 mana.","icon":"damagex3","flavorText":null,"name":"Jerator's Enchantment"},"Tc":{"tooltip":"Increases the chance that a monster happens to be a treasure chest by 2%.","icon":"treasureChance","flavorText":"Making good use of the lingering powers of a once-loathed ancient known as Thusia.","name":"Treasure Chest Chance"},"Z01":{"tooltip":"Automates Attempting a Boss.","icon":"gemAttemptBoss","flavorText":null,"name":"Automator Gem: Attempt Boss"},"qGp":{"tooltip":"Increases number of gold piles found by 30%.","icon":"goldPiles","flavorText":null,"name":"The Vision of Iris"},"S8":{"tooltip":"A stone that can activate during the first half of a zone.","icon":"zoneStart","flavorText":null,"name":"Automator Stone: Zone Start"},"T2":{"tooltip":"Restores 2 energy per second for 60 seconds.","icon":"energize","flavorText":"This skill consumes Mana to create Energy.","name":"Skill: Energize."},"Md":{"tooltip":"Multiplies the damage of Mana Crit by 125%","icon":"manaClick","flavorText":null,"name":"Mana Crit Damage"},"Q84":{"tooltip":"Makes your Big Clicks smaller. Small Clicks are half as strong, but there are twice as many of them.","icon":"damagex3","flavorText":null,"name":"Small Clicks"},"A7":{"tooltip":"Automates Mana Crit.","icon":"gemManaClick","flavorText":null,"name":"Automator Gem: Mana Crit"},"qBg":{"tooltip":"Increases your chance of finding bonus gold by 6%.","icon":"goldChance","flavorText":"When killing monsters, bonus gold may appear. This is a linear bonus, like Crit Chance.","name":"Fortuna's Luck"},"Q29":{"tooltip":"Consumes 1.25 mana per second to auto attacks 2.5 times per second, until you run out of mana.","icon":"damagex3","flavorText":"AutoAttackStorm is like Clickstorm, but does not replace it and can be used in conjunction with Clickstorm.","name":"AutoAttackStorm"},"A9":{"tooltip":"Automates Dash.","icon":"gemDash","flavorText":null,"name":"Automator Gem: Dash"},"S9":{"tooltip":"A stone that can activate during the second half of a zone.","icon":"zoneMiddle","flavorText":null,"name":"Automator Stone: Zone Middle"},"Q30":{"tooltip":"Energize becomes Managize, which restores 25% of your mana at the cost of 120 energy.","icon":"damagex3","flavorText":null,"name":"Managize"},"Bc":{"tooltip":"Increases the number of clicks empowered by Big Clicks by 1","icon":"bigClicks","flavorText":"They march loyally behind you in unison, each one prepared to sacrifice itself for your cause.","name":"More Big Clicks"},"Bg":{"tooltip":"Increases your chance of finding bonus gold by 2%.","icon":"goldChance","flavorText":"When killing monsters, bonus gold may appear. This is a linear bonus, like Crit Chance.","name":"Bonus Gold Chance"},"A8":{"tooltip":"Automates Reload.","icon":"gemReload","flavorText":null,"name":"Automator Gem: Reload"},"Q85":{"tooltip":"Haste increases the number of charges from Small Clicks, by the percentage of haste you have.","icon":"damagex3","flavorText":null,"name":"Expandable Small Clicks"},"T5":{"tooltip":"Causes your next click to deal 1000% damage.","icon":"hugeClicks","flavorText":"It stacks. Everything stacks.","name":"Skill: Huge Click"},"Q86":{"tooltip":"Small Clicks decreases the remaining cooldown of ClickTorrent by 1 second each.","icon":"damagex3","flavorText":null,"name":"Stormbringer"},"Z00":{"tooltip":"Unlocks an additional slot for the Automator.","icon":"gemAddSlot","flavorText":null,"name":"Automator Slot"},"qTc":{"tooltip":"Increases the chance that a monster is a treasure chest by 6%.","icon":"treasureChance","flavorText":null,"name":"Mimzee's Favor"},"Sc":{"tooltip":"A stone that can activate once every 4 seconds.","icon":"CD4S","flavorText":null,"name":"Automator Stone: 4s CD"},"T4":{"tooltip":"Consumes 1.25 energy per second to click 2.5 times per second, until you run out of energy.","icon":"clickstorm","flavorText":null,"name":"Skill: Clickstorm"},"qTg":{"tooltip":"Multiplies your gold received from treasure chests by 195%.","icon":"treasureGold","flavorText":null,"name":"Mimzee's Blessing"},"Q41":{"tooltip":"Consumes 1.25 energy per second to click 2.5 times per second, until you run out of energy. Doubles gold gained while active.","icon":"damagex3","flavorText":"Replaces Clickstorm.","name":"Golden Clicks"},"Aw":{"tooltip":"Switch to the next Automator Set.","icon":"gemSwitchNext","flavorText":null,"name":"Automator Gem: Next Set"},"":{"tooltip":"To Be Determined (temporarily gold)","icon":"goldx3","flavorText":null,"name":"TBD"},"Q42":{"tooltip":"Huge Click reduces the cost of items by a portion of your Huge Click's damage bonus for four seconds.","icon":"damagex3","flavorText":null,"name":"Huge Click Discount"},"Hd":{"tooltip":"Multiplies the damage done by Huge Click by 125%","icon":"hugeClicks","flavorText":"It actually gets bigger. But there is an unusual visual side effect that the rest of the world increases in size proportionally.","name":"Huger Huge Click"}}},"wizard":{"flavorClass":"The Cursed Wizard","name":"Wizard","flavor":"Coming Soon!","levelGraphObject":{"nodes":[],"edges":[]},"flavorName":"???","levelGraphNodeTypes":{}}}
